quicklock3/__init__.py
quicklock3/quicklock3.py
quicklock3-0.1.10.dist-info/LICENSE
quicklock3-0.1.10.dist-info/METADATA
quicklock3-0.1.10.dist-info/WHEEL
quicklock3-0.1.10.dist-info/top_level.txt
quicklock3-0.1.10.dist-info/RECORD
