Metadata-Version: 2.1
Name: quicklock3
Version: 0.1.10
Summary: A simple Python 3.x resource lock to ensure only one process at a time is operating with a particular resource.
Home-page: https://github.com/untixx/quicklock/
Author: Mathias Ziebarth (forked from Nate Ferrero)
Author-email: mathias.ziebarth@gmail.com
License: UNKNOWN
Download-URL: https://github.com/untixx/quicklock/tarball/0.1.9
Keywords: lock,locking,singleton,process,resource,exclusive lock
Platform: any
Requires-Dist: psutil (>=2.2)
